YehuoIMxRtKuKaifaShizhanZhinanFix1/README.md
YehuoIMxRtKuKaifaShizhanZhinanFix1/__init__.py
YehuoIMxRtKuKaifaShizhanZhinanFix1/__main__.py
YehuoIMxRtKuKaifaShizhanZhinanFix1/file.epub
YehuoIMxRtKuKaifaShizhanZhinanFix1/index.html
YehuoIMxRtKuKaifaShizhanZhinanFix1/css/__init__.py
YehuoIMxRtKuKaifaShizhanZhinanFix1/css/annotations.css
YehuoIMxRtKuKaifaShizhanZhinanFix1/css/main.css
YehuoIMxRtKuKaifaShizhanZhinanFix1/css/normalize.css
YehuoIMxRtKuKaifaShizhanZhinanFix1/css/popup.css
YehuoIMxRtKuKaifaShizhanZhinanFix1/font/__init__.py
YehuoIMxRtKuKaifaShizhanZhinanFix1/font/fontello.eot
YehuoIMxRtKuKaifaShizhanZhinanFix1/font/fontello.svg
YehuoIMxRtKuKaifaShizhanZhinanFix1/font/fontello.ttf
YehuoIMxRtKuKaifaShizhanZhinanFix1/font/fontello.woff
YehuoIMxRtKuKaifaShizhanZhinanFix1/img/__init__.py
YehuoIMxRtKuKaifaShizhanZhinanFix1/img/annotator-glyph-sprite.png
YehuoIMxRtKuKaifaShizhanZhinanFix1/img/annotator-icon-sprite.png
YehuoIMxRtKuKaifaShizhanZhinanFix1/img/apple-touch-icon.png
YehuoIMxRtKuKaifaShizhanZhinanFix1/img/cancelfullscreen.png
YehuoIMxRtKuKaifaShizhanZhinanFix1/img/close.png
YehuoIMxRtKuKaifaShizhanZhinanFix1/img/fullscreen.png
YehuoIMxRtKuKaifaShizhanZhinanFix1/img/loader.gif
YehuoIMxRtKuKaifaShizhanZhinanFix1/img/menu-icon.png
YehuoIMxRtKuKaifaShizhanZhinanFix1/img/save.png
YehuoIMxRtKuKaifaShizhanZhinanFix1/img/saved.png
YehuoIMxRtKuKaifaShizhanZhinanFix1/img/settings-s.png
YehuoIMxRtKuKaifaShizhanZhinanFix1/img/settings.png
YehuoIMxRtKuKaifaShizhanZhinanFix1/img/star.png
YehuoIMxRtKuKaifaShizhanZhinanFix1/js/__init__.py
YehuoIMxRtKuKaifaShizhanZhinanFix1/js/epub.js
YehuoIMxRtKuKaifaShizhanZhinanFix1/js/epub.min.js
YehuoIMxRtKuKaifaShizhanZhinanFix1/js/epub.min.map
YehuoIMxRtKuKaifaShizhanZhinanFix1/js/hooks.min.js
YehuoIMxRtKuKaifaShizhanZhinanFix1/js/hooks.min.map
YehuoIMxRtKuKaifaShizhanZhinanFix1/js/reader.js
YehuoIMxRtKuKaifaShizhanZhinanFix1/js/reader.js.map
YehuoIMxRtKuKaifaShizhanZhinanFix1/js/reader.min.js
yehuo_i_mx_rt_ku_kaifa_shizhan_zhinan_fix1-2025.3.24.1.dist-info/METADATA
yehuo_i_mx_rt_ku_kaifa_shizhan_zhinan_fix1-2025.3.24.1.dist-info/WHEEL
yehuo_i_mx_rt_ku_kaifa_shizhan_zhinan_fix1-2025.3.24.1.dist-info/entry_points.txt
yehuo_i_mx_rt_ku_kaifa_shizhan_zhinan_fix1-2025.3.24.1.dist-info/top_level.txt
yehuo_i_mx_rt_ku_kaifa_shizhan_zhinan_fix1-2025.3.24.1.dist-info/RECORD
